Workbook

Sheet Capa

Sheet Lançamentos
A1: Controle Financeiro para Estudantes com Renda Variável
A2: Data | B2: Tipo | C2: Categoria | D2: Descrição | E2: Valor | F2: Forma de Pagamento | G2: Status | H2: Mês | I2: Valor de Saída
A3: 46143 | B3: Entrada | C3: Apoio familiar | D3: Valor recebido da mãe | E3: 80 | F3: Pix | G3: Recebido | H3: Maio
A4: 46144 | B4: Saída | C4: Alimentação | D4: Lanche | E4: 18 | F4: Débito | G4: Pago | H4: Maio | I4: =IF(B4="Saída",E4," ") -> 18
A5: 46145 | B5: Saída | C5: Transporte | D5: Passagem | E5: 8 | F5: Dinheiro | G5: Pago | H5: Maio | I5: =IF(B5="Saída",E5," ") -> 8
A6: 46147 | B6: Entrada | C6: Apoio familiar | D6: Valor recebido do pai | E6: 50 | F6: Pix | G6: Recebido | H6: Maio | I6: =IF(B6="Saída",E6," ")
A7: 46148 | B7: Saída | C7: Curso | D7: Material de estudo | E7: 25 | F7: Pix | G7: Pago | H7: Maio | I7: =IF(B7="Saída",E7," ") -> 25
A8: 46150 | B8: Saída | C8: Lazer | D8: Cinema | E8: 22 | F8: Débito | G8: Pago | H8: Maio | I8: =IF(B8="Saída",E8," ") -> 22
A9: 46152 | B9: Entrada | C9: Presente | D9: Dinheiro recebido de aniversário | E9: 100 | F9: Dinheiro | G9: Recebido | H9: Maio | I9: =IF(B9="Saída",E9," ")
A10: 46154 | B10: Saída | C10: Alimentação | D10: Mercado | E10: 45 | F10: Pix | G10: Pago | H10: Maio | I10: =IF(B10="Saída",E10," ") -> 45
A11: 46156 | B11: Saída | C11: Farmácia | D11: Remédio | E11: 30 | F11: Débito | G11: Pago | H11: Maio | I11: =IF(B11="Saída",E11," ") -> 30
A12: 46158 | B12: Saída | C12: Transporte | D12: Uber | E12: 20 | F12: Crédito | G12: Pago | H12: Maio | I12: =IF(B12="Saída",E12," ") -> 20

Sheet Resumo
A1: Resumo Financeiro | E1: Gastos por Categoria
A2: Total de Entradas | B2: Total de Saídas | C2: Saldo Final | E2: Categoria | F2: Total gasto
A3: =SUMIF(Lançamentos!B:B,"Entrada",Lançamentos!E:E) -> 230 | B3: =SUMIF(Lançamentos!B:B,"Saída",Lançamentos!E:E) -> 168 | C3: =A3-B3 -> 62 | E3: Alimentação | F3: =SUMIF(Lançamentos!C:C,E3,Lançamentos!E:E) -> 63
A4: Maior Gasto | B4: Menor Gasto | C4: Média de Gastos | E4: Transporte | F4: =SUMIF(Lançamentos!C:C,E4,Lançamentos!E:E) -> 28
A5: =MAX(Lançamentos!I:I) -> 45 | B5: =MIN(Lançamentos!I:I) -> 8 | C5: =AVERAGE(Lançamentos!I:I) -> 24 | E5: Curso | F5: =SUMIF(Lançamentos!C:C,E5,Lançamentos!E:E) -> 25
E6: Lazer | F6: =SUMIF(Lançamentos!C:C,E6,Lançamentos!E:E) -> 22
E7: Farmácia | F7: =SUMIF(Lançamentos!C:C,E7,Lançamentos!E:E) -> 30
E8: % de Gastos sobre Entradas
E9: =B3/A3 -> 0.73043478
